vizly/__init__.py
vizly/cli.py
vizly/demo_comprehensive.py
vizly/exceptions.py
vizly/figure.py
vizly/interaction3d.py
vizly/theme.py
vizly/vizly_isolation_config.py
vizly/cae/__init__.py
vizly/cae/analysis.py
vizly/cae/animation.py
vizly/cae/fields.py
vizly/cae/geometry.py
vizly/cae/mesh.py
vizly/charts/__init__.py
vizly/charts/advanced.py
vizly/charts/bar.py
vizly/charts/base.py
vizly/charts/box.py
vizly/charts/datascience.py
vizly/charts/engineering.py
vizly/charts/financial.py
vizly/charts/histogram.py
vizly/charts/line.py
vizly/charts/pure_charts.py
vizly/charts/scatter.py
vizly/charts/surface.py
vizly/core/__init__.py
vizly/core/config.py
vizly/core/performance.py
vizly/core/renderer.py
vizly/core/streaming.py
vizly/engineering/__init__.py
vizly/engineering/bode.py
vizly/engineering/stress.py
vizly/enterprise/__init__.py
vizly/enterprise/admin.py
vizly/enterprise/api.py
vizly/enterprise/benchmarks.py
vizly/enterprise/charts.py
vizly/enterprise/connectors.py
vizly/enterprise/dashboard.py
vizly/enterprise/dashboard_server.py
vizly/enterprise/docs_server.py
vizly/enterprise/exports.py
vizly/enterprise/gis.py
vizly/enterprise/licensing.py
vizly/enterprise/metrics_aggregator.py
vizly/enterprise/monitoring.py
vizly/enterprise/performance.py
vizly/enterprise/security.py
vizly/enterprise/server.py
vizly/enterprise/testing.py
vizly/enterprise/themes.py
vizly/gpu/__init__.py
vizly/gpu/acceleration.py
vizly/gpu/backends.py
vizly/gpu/kernels.py
vizly/gpu/memory.py
vizly/interaction3d/__init__.py
vizly/interaction3d/advanced.py
vizly/interaction3d/animation.py
vizly/interaction3d/camera.py
vizly/interaction3d/gestures.py
vizly/interaction3d/manipulation.py
vizly/interaction3d/navigation.py
vizly/interaction3d/scene.py
vizly/interaction3d/scene_manager.py
vizly/interaction3d/selection.py
vizly/interaction3d/vr.py
vizly/interactive/__init__.py
vizly/interactive/base.py
vizly/interactive/controls.py
vizly/interactive/dashboard.py
vizly/interactive/streaming.py
vizly-1.1.0.dist-info/licenses/LICENSE
vizly-1.1.0.dist-info/METADATA
vizly-1.1.0.dist-info/WHEEL
vizly-1.1.0.dist-info/entry_points.txt
vizly-1.1.0.dist-info/top_level.txt
vizly-1.1.0.dist-info/RECORD
