Metadata-Version: 2.4
Name: vizly
Version: 1.1.0
Summary: Commercial high-performance visualization library with GPU acceleration, VR/AR support, and zero dependencies
Home-page: https://github.com/vizly/vizly
Author: Infinidatum Corporation
Author-email: Infinidatum Corporation <durai@infinidatum.net>
Maintainer-email: Infinidatum Corporation <durai@infinidatum.net>
License: Commercial License - Contact durai@infinidatum.net
Project-URL: Homepage, https://github.com/vizly/vizly
Project-URL: Documentation, https://vizly.readthedocs.io/
Project-URL: Repository, https://github.com/vizly/vizly
Project-URL: Bug Tracker, https://github.com/vizly/vizly/issues
Project-URL: Examples, https://github.com/vizly/vizly/tree/main/examples
Keywords: visualization,plotting,charts,graphs,data-science,matplotlib-alternative,plotly-alternative,zero-dependencies,3d-visualization,interactive-charts,financial-charts,real-time-plotting,high-performance,pure-python,scientific-visualization,engineering-plots,dashboard,gpu-acceleration,vr,ar,webxr,streaming,commercial
Classifier: Development Status :: 5 - Production/Stable
Classifier: Intended Audience :: Developers
Classifier: Intended Audience :: Science/Research
Classifier: Intended Audience :: Financial and Insurance Industry
Classifier: Intended Audience :: Education
Classifier: Topic :: Scientific/Engineering :: Visualization
Classifier: Topic :: Scientific/Engineering :: Information Analysis
Classifier: Topic :: Multimedia :: Graphics
Classifier: Topic :: Software Development :: Libraries :: Python Modules
Classifier: License :: Other/Proprietary License
Classifier: Programming Language :: Python :: 3
Classifier: Programming Language :: Python :: 3.7
Classifier: Programming Language :: Python :: 3.8
Classifier: Programming Language :: Python :: 3.9
Classifier: Programming Language :: Python :: 3.10
Classifier: Programming Language :: Python :: 3.11
Classifier: Programming Language :: Python :: 3.12
Classifier: Operating System :: OS Independent
Classifier: Environment :: Console
Classifier: Environment :: Web Environment
Requires-Python: >=3.7
License-File: LICENSE
Requires-Dist: numpy>=1.19.0
Requires-Dist: matplotlib>=3.5.0
Requires-Dist: pandas>=1.3.0
Requires-Dist: scipy>=1.7.0
Requires-Dist: psutil>=5.8.0
Requires-Dist: joblib>=1.1.0
Requires-Dist: websockets>=10.0
Requires-Dist: aiohttp>=3.8.0
Requires-Dist: pillow>=8.0.0
Requires-Dist: opencv-python>=4.5.0
Provides-Extra: dev
Requires-Dist: pytest>=6.0.0; extra == "dev"
Requires-Dist: pytest-cov>=2.10.0; extra == "dev"
Requires-Dist: black>=21.0.0; extra == "dev"
Requires-Dist: ruff>=0.1.0; extra == "dev"
Requires-Dist: mypy>=0.800; extra == "dev"
Requires-Dist: twine>=4.0.0; extra == "dev"
Requires-Dist: build>=0.10.0; extra == "dev"
Provides-Extra: gpu
Requires-Dist: cupy>=9.0.0; extra == "gpu"
Requires-Dist: pyopencl>=2021.1.0; extra == "gpu"
Provides-Extra: enterprise
Requires-Dist: redis>=4.0.0; extra == "enterprise"
Requires-Dist: celery>=5.0.0; extra == "enterprise"
Requires-Dist: sqlalchemy>=1.4.0; extra == "enterprise"
Dynamic: author
Dynamic: home-page
Dynamic: license-file
Dynamic: requires-python
